reviews-platzi/__init__.py
reviews-platzi/rplatzi.py
reviews_platzi/__init__.py
reviews_platzi/rplatzi.py
reviews_platzi-0.1.9.dist-info/METADATA
reviews_platzi-0.1.9.dist-info/WHEEL
reviews_platzi-0.1.9.dist-info/entry_points.txt
reviews_platzi-0.1.9.dist-info/top_level.txt
reviews_platzi-0.1.9.dist-info/RECORD
